Metadata-Version: 2.1
Name: lyapynov
Version: 1.0.1
Summary: A python package to compute Lyapunov exponents, covariant Lyapunov vectors (CLV) and adjoints of a dynamical system.
Home-page: https://github.com/ThomasSavary08/Lyapynov
Author: Thomas Savary
Author-email: savarythomas2102@gmail.com
Keywords: Lyapunov,Lyapunov exponents,LCE,Covariant Lyapunov vectors,CLV,Dynamical systems,ODE
Classifier: Development Status :: 3 - Alpha
Classifier: Intended Audience :: Science/Research
Classifier: Topic :: Scientific/Engineering
Classifier: Topic :: Scientific/Engineering :: Mathematics
Classifier: Topic :: Scientific/Engineering :: Physics
Classifier: Programming Language :: Python :: 3
Requires-Python: >=3.8
